mtnlpmodel/__init__.py
mtnlpmodel/core.py
mtnlpmodel/train.py
mtnlpmodel/server/__init__.py
mtnlpmodel/server/evaluation/__init__.py
mtnlpmodel/server/evaluation/evaluation.py
mtnlpmodel/server/inference/__init__.py
mtnlpmodel/server/inference/inference.py
mtnlpmodel/utils/__init__.py
mtnlpmodel/utils/input_process_util.py
mtnlpmodel/utils/io_utils.py
mtnlpmodel/utils/loss_func_util.py
mtnlpmodel/utils/lrset_util.py
mtnlpmodel/utils/model_util.py
mtnlpmodel/utils/optimizer_util.py
mtnlpmodel/utils/triplet_loss_util.py
mtnlp_model-0.0.1.dist-info/LICENSE
mtnlp_model-0.0.1.dist-info/METADATA
mtnlp_model-0.0.1.dist-info/WHEEL
mtnlp_model-0.0.1.dist-info/top_level.txt
mtnlp_model-0.0.1.dist-info/RECORD
